p43_test_automation/__init__.py
p43_test_automation/__main__.py
p43_test_automation/common.py
p43_test_automation/run_tests.py
p43_test_automation/data/files/over_6mb/bmp/bmp_6.12mb.bmp
p43_test_automation/data/files/under_6mb/bmp/bmp_32kb.bmp
p43_test_automation/data/files/under_6mb/bmp/bmp_5.93mb.bmp
p43_test_automation/data/files/under_6mb/corrupt/Corrupted_jpeg_png_mag_no
p43_test_automation/data/files/under_6mb/doc/doc_embedded_images_12kb.docx
p43_test_automation/data/files/under_6mb/harmless_macro/xls/CalcTest.xls
p43_test_automation/data/files/under_6mb/txt/txt_1kb.txt
p43_test_automation/integration_tests/__init__.py
p43_test_automation/integration_tests/rebuild/__init__.py
p43_test_automation/integration_tests/rebuild/test_rebuild_base64.py
p43_test_automation/integration_tests/rebuild/test_rebuild_file.py
p43_test_automation/integration_tests/rebuild/test_rebuild_url.py
glasswall_azure_product_test_automation-0.3.2.dist-info/LICENSE
glasswall_azure_product_test_automation-0.3.2.dist-info/METADATA
glasswall_azure_product_test_automation-0.3.2.dist-info/WHEEL
glasswall_azure_product_test_automation-0.3.2.dist-info/entry_points.txt
glasswall_azure_product_test_automation-0.3.2.dist-info/top_level.txt
glasswall_azure_product_test_automation-0.3.2.dist-info/RECORD
