Metadata-Version: 2.1
Name: glasswall-azure-product-test-automation
Version: 0.3.2
Summary: A small package for testing Glasswall Azure products
Home-page: https://github.com/filetrust/azure-product-test-automation
Author: AngusWR
Author-email: aroberts@glasswallsolutions.com
License: UNKNOWN
Platform: UNKNOWN
Classifier: Programming Language :: Python :: 3.8
Requires-Python: >=3.6
Requires-Dist: requests (>=2.22.0)
